PyDelegator/delegator_manager.py
pydelegator-0.3.1.dist-info/METADATA
pydelegator-0.3.1.dist-info/WHEEL
pydelegator-0.3.1.dist-info/RECORD
