Metadata-Version: 2.1
Name: pydelegator
Version: 0.3.1
Summary: This project add able to work with delegators in python
License: MIT
Author: dima-on
Author-email: sinica911@gmail.com
Requires-Python: >=3.9,<4.0
Classifier: License :: OSI Approved :: MIT License
Classifier: Programming Language :: Python :: 3
Classifier: Programming Language :: Python :: 3.9
Classifier: Programming Language :: Python :: 3.10
Classifier: Programming Language :: Python :: 3.11
Classifier: Programming Language :: Python :: 3.12
Classifier: Programming Language :: Python :: 3.13
